LICENSE
README.rst
requirements.txt
setup.py
icontract_hypothesis/__init__.py
icontract_hypothesis/__main__.py
icontract_hypothesis/py.typed
icontract_hypothesis.egg-info/PKG-INFO
icontract_hypothesis.egg-info/SOURCES.txt
icontract_hypothesis.egg-info/dependency_links.txt
icontract_hypothesis.egg-info/entry_points.txt
icontract_hypothesis.egg-info/requires.txt
icontract_hypothesis.egg-info/top_level.txt
icontract_hypothesis/pyicontract_hypothesis/__init__.py
icontract_hypothesis/pyicontract_hypothesis/_general.py
icontract_hypothesis/pyicontract_hypothesis/_ghostwrite.py
icontract_hypothesis/pyicontract_hypothesis/_test.py
icontract_hypothesis/pyicontract_hypothesis/main.py
test_samples/__init__.py
test_samples/pyicontract_hypothesis/__init__.py
test_samples/pyicontract_hypothesis/sample_invalid_module.py
test_samples/pyicontract_hypothesis/sample_library.py
test_samples/pyicontract_hypothesis/sample_module.py
test_samples/pyicontract_hypothesis/well_formatted_with_two_arguments.py
tests/pyicontract_hypothesis/__init__.py
tests/pyicontract_hypothesis/test_general.py
tests/pyicontract_hypothesis/test_ghostwrite.py
tests/pyicontract_hypothesis/test_invalid_arguments.py
tests/pyicontract_hypothesis/test_test.py
tests/strategy_inference/__init__.py
tests/strategy_inference/test_matching_bounds.py
tests/strategy_inference/test_matching_regex.py
tests/strategy_inference/test_strategy_inference.py
tests_3_7/__init__.py