Metadata-Version: 2.1
Name: icontract-hypothesis
Version: 1.1.5
Summary: Combine contracts and automatic testing.
Home-page: https://github.com/mristin/icontract-hypothesis
Author: Marko Ristin
Author-email: marko@ristin.ch
License: License :: OSI Approved :: MIT License
Keywords: design-by-contract contracts automatic testing property-based
Platform: UNKNOWN
Classifier: Development Status :: 5 - Production/Stable
Classifier: License :: OSI Approved :: MIT License
Classifier: Programming Language :: Python :: 3.6
Classifier: Programming Language :: Python :: 3.7
Classifier: Programming Language :: Python :: 3.8
Classifier: Framework :: Hypothesis
Provides-Extra: dev
